{
  "peers": {
    "thor": {
      "talent": 0.5,
      "training": 0.5,
      "temperament": 0.0,
      "interactions": 45521,
      "last_updated": 1774963041.6206548
    },
    "sprout": {
      "talent": 0.5,
      "training": 0.5,
      "temperament": 0.0,
      "interactions": 45517,
      "last_updated": 1774963043.622931
    },
    "legion": {
      "talent": 0.5,
      "training": 0.5,
      "temperament": 0.0,
      "interactions": 45515,
      "last_updated": 1774963045.6251497
    },
    "mcnugget": {
      "talent": 0.5,
      "training": 0.5,
      "temperament": 0.0,
      "interactions": 45510,
      "last_updated": 1774963047.6316664
    },
    "cbp": {
      "talent": 0.5,
      "training": 0.5,
      "temperament": 0.0,
      "interactions": 45505,
      "last_updated": 1774963030.1434257
    }
  },
  "last_updated": 1774963047.6370645
}