{
  "peers": {
    "thor": {
      "talent": 0.5,
      "training": 0.5,
      "temperament": 0.0,
      "interactions": 66779,
      "last_updated": 1774928099.372119
    },
    "sprout": {
      "talent": 0.5,
      "training": 0.5,
      "temperament": 0.0,
      "interactions": 66754,
      "last_updated": 1774928101.3752298
    },
    "legion": {
      "talent": 0.5,
      "training": 0.5,
      "temperament": 0.0,
      "interactions": 66744,
      "last_updated": 1774928101.376221
    },
    "nomad": {
      "talent": 0.5,
      "training": 0.5,
      "temperament": 0.0,
      "interactions": 66735,
      "last_updated": 1774928101.376828
    },
    "cbp": {
      "talent": 0.5,
      "training": 0.5,
      "temperament": 0.0,
      "interactions": 66721,
      "last_updated": 1774928067.312692
    }
  },
  "last_updated": 1774928101.377186
}